rajaongkir/__init__.py
rajaongkir/__main__.py
rajaongkir/client.py
rajaongkir/endpoint.py
rajaongkir/errors.py
rajaongkir_py-1.0.1.dist-info/LICENSE
rajaongkir_py-1.0.1.dist-info/METADATA
rajaongkir_py-1.0.1.dist-info/WHEEL
rajaongkir_py-1.0.1.dist-info/entry_points.txt
rajaongkir_py-1.0.1.dist-info/top_level.txt
rajaongkir_py-1.0.1.dist-info/RECORD
