Metadata-Version: 2.1
Name: rajaongkir-py
Version: 1.0.1
Summary: RajaOngkir API Wrapper
Author-email: Danang Haris Setiawan <mr.danangharissetiawan@gmail.com>
License: The MIT License (MIT)
Project-URL: Homepage, https://github.com/danangharissetiawan/raja-ongkir
Keywords: ongkir,raja ongkir,api,wrapper,raja ongkir api
Classifier: Programming Language :: Python :: 3
Classifier: License :: OSI Approved :: MIT License
Classifier: Operating System :: OS Independent
Requires-Python: >=3.9
License-File: LICENSE
Requires-Dist: requests (==2.28.1)
Requires-Dist: python-dotenv (==0.20.0)
Provides-Extra: dev
Requires-Dist: black ; extra == 'dev'
Requires-Dist: bumpver ; extra == 'dev'
Requires-Dist: isort ; extra == 'dev'
Requires-Dist: pip-tools ; extra == 'dev'
Requires-Dist: pytest ; extra == 'dev'
